[
  {
    "full_name": "dagger/dagger",
    "stargazers_count": 14898,
    "open_issues_count": 795,
    "forks_count": 812
  },
  {
    "full_name": "hydrostack/hydro",
    "stargazers_count": 869,
    "open_issues_count": 18,
    "forks_count": 30
  },
  {
    "full_name": "regie2197/cypress-test-automation-2025",
    "stargazers_count": 1,
    "open_issues_count": 0,
    "forks_count": 19
  },
  {
    "full_name": "break-into-data/ai-engineer-toolkit",
    "stargazers_count": 2052,
    "open_issues_count": 2,
    "forks_count": 405
  },
  {
    "full_name": "furey/mongodb-lens",
    "stargazers_count": 188,
    "open_issues_count": 4,
    "forks_count": 24
  },
  {
    "full_name": "juliangarnier/anime",
    "stargazers_count": 65063,
    "open_issues_count": 78,
    "forks_count": 4355
  },
  {
    "full_name": "nuejs/nue",
    "stargazers_count": 8831,
    "open_issues_count": 73,
    "forks_count": 258
  },
  {
    "full_name": "evolutionary-architecture/evolutionary-architecture-by-example",
    "stargazers_count": 2893,
    "open_issues_count": 9,
    "forks_count": 428
  },
  {
    "full_name": "codespaces-contrib/azdo-in-codespaces",
    "stargazers_count": 27,
    "open_issues_count": 1,
    "forks_count": 14
  },
  {
    "full_name": "al1abb/invoify",
    "stargazers_count": 6007,
    "open_issues_count": 35,
    "forks_count": 628
  },
  {
    "full_name": "magicuidesign/magicui",
    "stargazers_count": 19312,
    "open_issues_count": 18,
    "forks_count": 858
  },
  {
    "full_name": "instantdb/instant",
    "stargazers_count": 9366,
    "open_issues_count": 14,
    "forks_count": 302
  },
  {
    "full_name": "microsoft/Generative-AI-for-beginners-dotnet",
    "stargazers_count": 1990,
    "open_issues_count": 0,
    "forks_count": 1564
  },
  {
    "full_name": "payloadcms/payload",
    "stargazers_count": 38397,
    "open_issues_count": 755,
    "forks_count": 3044
  },
  {
    "full_name": "greenpau/caddy-security",
    "stargazers_count": 1943,
    "open_issues_count": 201,
    "forks_count": 89
  },
  {
    "full_name": "DavidHDev/react-bits",
    "stargazers_count": 29358,
    "open_issues_count": 2,
    "forks_count": 1262
  },
  {
    "full_name": "dobizz/PyLDT",
    "stargazers_count": 3,
    "open_issues_count": 0,
    "forks_count": 1
  },
  {
    "full_name": "menees/Chords",
    "stargazers_count": 20,
    "open_issues_count": 0,
    "forks_count": 1
  },
  {
    "full_name": "ChrisTitusTech/winutil",
    "stargazers_count": 41960,
    "open_issues_count": 253,
    "forks_count": 2245
  },
  {
    "full_name": "IridiumIO/CompactGUI",
    "stargazers_count": 6745,
    "open_issues_count": 39,
    "forks_count": 277
  },
  {
    "full_name": "microsoft/Web-Dev-For-Beginners",
    "stargazers_count": 92483,
    "open_issues_count": 39,
    "forks_count": 14330
  },
  {
    "full_name": "aebibtech/box-dl-gui",
    "stargazers_count": 7,
    "open_issues_count": 0,
    "forks_count": 1
  },
  {
    "full_name": "aebibtech/win-move-shell-folders",
    "stargazers_count": 2,
    "open_issues_count": 0,
    "forks_count": 0
  },
  {
    "full_name": "aebibtech/win-transfer-to-ssd",
    "stargazers_count": 1,
    "open_issues_count": 0,
    "forks_count": 0
  },
  {
    "full_name": "farag2/Utilities",
    "stargazers_count": 647,
    "open_issues_count": 0,
    "forks_count": 117
  },
  {
    "full_name": "kamranahmedse/developer-roadmap",
    "stargazers_count": 342103,
    "open_issues_count": 111,
    "forks_count": 43230
  },
  {
    "full_name": "mattcone/markdown-guide",
    "stargazers_count": 3814,
    "open_issues_count": 37,
    "forks_count": 679
  }
]