[
  {
    "full_name": "ChrisTitusTech/winutil",
    "stargazers_count": 23981,
    "open_issues_count": 156,
    "forks_count": 1463
  },
  {
    "full_name": "IridiumIO/CompactGUI",
    "stargazers_count": 5082,
    "open_issues_count": 24,
    "forks_count": 236
  },
  {
    "full_name": "microsoft/Web-Dev-For-Beginners",
    "stargazers_count": 83538,
    "open_issues_count": 112,
    "forks_count": 12341
  },
  {
    "full_name": "aebibtech/box-dl-gui",
    "stargazers_count": 5,
    "open_issues_count": 0,
    "forks_count": 1
  },
  {
    "full_name": "aebibtech/win-move-shell-folders",
    "stargazers_count": 2,
    "open_issues_count": 0,
    "forks_count": 0
  },
  {
    "full_name": "aebibtech/win-transfer-to-ssd",
    "stargazers_count": 1,
    "open_issues_count": 0,
    "forks_count": 0
  },
  {
    "full_name": "farag2/Utilities",
    "stargazers_count": 517,
    "open_issues_count": 0,
    "forks_count": 97
  },
  {
    "full_name": "kamranahmedse/developer-roadmap",
    "stargazers_count": 296837,
    "open_issues_count": 44,
    "forks_count": 39111
  },
  {
    "full_name": "mattcone/markdown-guide",
    "stargazers_count": 3311,
    "open_issues_count": 35,
    "forks_count": 620
  }
]